<?xml version="1.0" encoding="utf-8"?>
<LocalizeDictionary xmlns:xsi="http://www.w3.org/2001/XMLSchema-instance" xmlns:xsd="http://www.w3.org/2001/XMLSchema">
  <LocalizeList>
    <LocalizeInfo>
      <Key>Setting</Key>
      <Value>Asetus</Value>
      <Comment>Settings</Comment>
      <Link />
      <FontSize>12</FontSize>
      <FontName>Segoe UI</FontName>
      <MaxNumber>12</MaxNumber>
    </LocalizeInfo>
    <LocalizeInfo>
      <Key>BackupImage</Key>
      <Value>Tutkimus</Value>
      <Comment>Study</Comment>
      <Link />
      <FontSize>12</FontSize>
      <FontName>Segoe UI</FontName>
      <MaxNumber>12</MaxNumber>
    </LocalizeInfo>
    <LocalizeInfo>
      <Key>BackupData</Key>
      <Value>DB</Value>
      <Comment>Data</Comment>
      <Link />
      <FontSize>12</FontSize>
      <FontName>Segoe UI</FontName>
      <MaxNumber>12</MaxNumber>
    </LocalizeInfo>
    <LocalizeInfo>
      <Key>BackupLog</Key>
      <Value>Loki</Value>
      <Comment>Log</Comment>
      <Link />
      <FontSize>12</FontSize>
      <FontName>Segoe UI</FontName>
      <MaxNumber>12</MaxNumber>
    </LocalizeInfo>
    <LocalizeInfo>
      <Key>SaveLocation</Key>
      <Value>Tallenna sijainti</Value>
      <Comment>Save Location</Comment>
      <Link />
      <FontSize>12</FontSize>
      <FontName>Segoe UI</FontName>
      <MaxNumber>12</MaxNumber>
    </LocalizeInfo>
    <LocalizeInfo>
      <Key>Browse</Key>
      <Value>Selaa</Value>
      <Comment>Browse</Comment>
      <Link />
      <FontSize>12</FontSize>
      <FontName>Segoe UI</FontName>
      <MaxNumber>12</MaxNumber>
    </LocalizeInfo>
    <LocalizeInfo>
      <Key>SpecifyDuration</Key>
      <Value>Määritä kesto</Value>
      <Comment>Specify Duration</Comment>
      <Link />
      <FontSize>12</FontSize>
      <FontName>Segoe UI</FontName>
      <MaxNumber>12</MaxNumber>
    </LocalizeInfo>
    <LocalizeInfo>
      <Key>DeletePersonalInformation</Key>
      <Value>Suojaa henkilökohtaiset tiedot</Value>
      <Comment>Protect Personal Information</Comment>
      <Link />
      <FontSize>12</FontSize>
      <FontName>Segoe UI</FontName>
      <MaxNumber>12</MaxNumber>
    </LocalizeInfo>
    <LocalizeInfo>
      <Key>StudyList</Key>
      <Value>Tutkimusluettelo</Value>
      <Comment>Study List</Comment>
      <Link />
      <FontSize>12</FontSize>
      <FontName>Segoe UI</FontName>
      <MaxNumber>12</MaxNumber>
    </LocalizeInfo>
    <LocalizeInfo>
      <Key>PatientIDHeader</Key>
      <Value>Potilastunnus</Value>
      <Comment>Patient ID</Comment>
      <Link />
      <FontSize>12</FontSize>
      <FontName>Segoe UI</FontName>
      <MaxNumber>12</MaxNumber>
    </LocalizeInfo>
    <LocalizeInfo>
      <Key>PatientNameHeader</Key>
      <Value>Potilaan nimi</Value>
      <Comment>Patient Name</Comment>
      <Link />
      <FontSize>12</FontSize>
      <FontName>Segoe UI</FontName>
      <MaxNumber>12</MaxNumber>
    </LocalizeInfo>
    <LocalizeInfo>
      <Key>StudyDateHeader</Key>
      <Value>Tutkimuksen päivämäärä</Value>
      <Comment>Study Date</Comment>
      <Link />
      <FontSize>12</FontSize>
      <FontName>Segoe UI</FontName>
      <MaxNumber>12</MaxNumber>
    </LocalizeInfo>
    <LocalizeInfo>
      <Key>StudyTimeHeader</Key>
      <Value>Tutkimuksen kellonaika</Value>
      <Comment>Study Time</Comment>
      <Link />
      <FontSize>12</FontSize>
      <FontName>Segoe UI</FontName>
      <MaxNumber>12</MaxNumber>
    </LocalizeInfo>
    <LocalizeInfo>
      <Key>AccessionNoHeader</Key>
      <Value>Lisäysnumero</Value>
      <Comment>Accession No</Comment>
      <Link />
      <FontSize>12</FontSize>
      <FontName>Segoe UI</FontName>
      <MaxNumber>12</MaxNumber>
    </LocalizeInfo>
    <LocalizeInfo>
      <Key>ImageCountHeader</Key>
      <Value>Kuvien määrä</Value>
      <Comment>Image Count</Comment>
      <Link />
      <FontSize>12</FontSize>
      <FontName>Segoe UI</FontName>
      <MaxNumber>12</MaxNumber>
    </LocalizeInfo>
    <LocalizeInfo>
      <Key>OutputData</Key>
      <Value>Tulostustietojen koko</Value>
      <Comment>Output Data Size</Comment>
      <Link />
      <FontSize>12</FontSize>
      <FontName>Segoe UI</FontName>
      <MaxNumber>12</MaxNumber>
    </LocalizeInfo>
    <LocalizeInfo>
      <Key>Execute</Key>
      <Value>Suorita</Value>
      <Comment>Execute</Comment>
      <Link />
      <FontSize>12</FontSize>
      <FontName>Segoe UI</FontName>
      <MaxNumber>12</MaxNumber>
    </LocalizeInfo>
    <LocalizeInfo>
      <Key>Close</Key>
      <Value>Sulje</Value>
      <Comment>Close</Comment>
      <Link />
      <FontSize>12</FontSize>
      <FontName>Segoe UI</FontName>
      <MaxNumber>64</MaxNumber>
    </LocalizeInfo>
    <LocalizeInfo>
      <Key>TitleCaption</Key>
      <Value>Varmuuskopioi</Value>
      <Comment>TitleCaption</Comment>
      <Link />
      <FontSize>12</FontSize>
      <FontName>Segoe UI</FontName>
      <MaxNumber>64</MaxNumber>
    </LocalizeInfo>
    <LocalizeInfo>
      <Key>SelectTypeMessage</Key>
      <Value>Valitse varmuuskopioitava tyyppi.</Value>
      <Comment>SelectTypeMessage</Comment>
      <Link />
      <FontSize>12</FontSize>
      <FontName>Segoe UI</FontName>
      <MaxNumber>64</MaxNumber>
    </LocalizeInfo>
    <LocalizeInfo>
      <Key>SaveLocationMessage</Key>
      <Value>Valitse tallennussijainti</Value>
      <Comment>SaveLocationMessage</Comment>
      <Link />
      <FontSize>12</FontSize>
      <FontName>Segoe UI</FontName>
      <MaxNumber>64</MaxNumber>
    </LocalizeInfo>
    <LocalizeInfo>
      <Key>SelectStudyMessage</Key>
      <Value>Valitse tutkimus tutkimusluettelosta</Value>
      <Comment>SelectStudyMessage</Comment>
      <Link />
      <FontSize>12</FontSize>
      <FontName>Segoe UI</FontName>
      <MaxNumber>64</MaxNumber>
    </LocalizeInfo>
    <LocalizeInfo>
      <Key>MessageBoxTitle</Key>
      <Value>Varmuuskopioi</Value>
      <Comment>MessageBoxTitle</Comment>
      <Link />
      <FontSize>12</FontSize>
      <FontName>Segoe UI</FontName>
      <MaxNumber>64</MaxNumber>
    </LocalizeInfo>
    <LocalizeInfo>
      <Key>BackupConfirmationMessage</Key>
      <Value>Haluatko varmuuskopioida valitut tiedostot?</Value>
      <Comment>BackupConfirmationMessage</Comment>
      <Link />
      <FontSize>12</FontSize>
      <FontName>Segoe UI</FontName>
      <MaxNumber>64</MaxNumber>
    </LocalizeInfo>
    <LocalizeInfo>
      <Key>InvalidPathMessage</Key>
      <Value>Annettu polku ei kelpaa.</Value>
      <Comment>InvalidPathMessage</Comment>
      <Link />
      <FontSize>12</FontSize>
      <FontName>Segoe UI</FontName>
      <MaxNumber>64</MaxNumber>
    </LocalizeInfo>
    <LocalizeInfo>
      <Key>ReplaceStudyZipMessage</Key>
      <Value>Haluatko korvata nykyisen tutkimuksen zip-tiedostot?</Value>
      <Comment>ReplaceStudyZipMessage</Comment>
      <Link />
      <FontSize>12</FontSize>
      <FontName>Segoe UI</FontName>
      <MaxNumber>64</MaxNumber>
    </LocalizeInfo>
    <LocalizeInfo>
      <Key>LogFilesNotFoundMessage</Key>
      <Value>Määritetystä kestosta ei löytynyt lokitiedostoja</Value>
      <Comment>LogFilesNotFoundMessage</Comment>
      <Link />
      <FontSize>12</FontSize>
      <FontName>Segoe UI</FontName>
      <MaxNumber>64</MaxNumber>
    </LocalizeInfo>
    <LocalizeInfo>
      <Key>StudyAbortedMessage</Key>
      <Value>Käyttäjä on keskeyttänyt tutkimuksen varmuuskopioinnin</Value>
      <Comment>StudyAbortedMessage</Comment>
      <Link />
      <FontSize>12</FontSize>
      <FontName>Segoe UI</FontName>
      <MaxNumber>64</MaxNumber>
    </LocalizeInfo>
    <LocalizeInfo>
      <Key>BackupCompletedMessage</Key>
      <Value>Varmuuskopiointi suoritettu</Value>
      <Comment>BackupCompletedMessage</Comment>
      <Link />
      <FontSize>12</FontSize>
      <FontName>Segoe UI</FontName>
      <MaxNumber>64</MaxNumber>
    </LocalizeInfo>
    <LocalizeInfo>
      <Key>SelectAll</Key>
      <Value>Select All</Value>
      <Comment>Select All</Comment>
      <Link />
      <FontSize>12</FontSize>
      <FontName>Segoe UI</FontName>
      <MaxNumber>64</MaxNumber>
    </LocalizeInfo>
    <LocalizeInfo>
      <Key>ReleaseAll</Key>
      <Value>Release All</Value>
      <Comment>Release All</Comment>
      <Link />
      <FontSize>12</FontSize>
      <FontName>Segoe UI</FontName>
      <MaxNumber>64</MaxNumber>
    </LocalizeInfo>
  </LocalizeList>
</LocalizeDictionary>