<?xml version="1.0" encoding="utf-8"?>
<LocalizeDictionary xmlns:xsi="http://www.w3.org/2001/XMLSchema-instance" xmlns:xsd="http://www.w3.org/2001/XMLSchema">
  <LocalizeList>
    <LocalizeInfo>
      <Key>LineWidthErrMessage</Key>
      <Value>length should not less than 1</Value>
      <Comment>Outline</Comment>
      <Link />
      <FontSize>12</FontSize>
      <FontName>Meiryo</FontName>
      <MaxNumber>12</MaxNumber>
</LocalizeInfo>



<LocalizeInfo>
      <Key>StampItem</Key>
      <Value>StampItem</Value>
      <Comment>Outline</Comment>
      <Link />
      <FontSize>12</FontSize>
      <FontName>Meiryo</FontName>
      <MaxNumber>12</MaxNumber>
</LocalizeInfo>


<LocalizeInfo>
      <Key>FontSizeErrMessage</Key>
      <Value>Line font size(s) are out of range. It must set within the Limitation.(1~20)</Value>
      <Comment>Outline</Comment>
      <Link />
      <FontSize>12</FontSize>
      <FontName>Meiryo</FontName>
      <MaxNumber>12</MaxNumber>
    </LocalizeInfo>


<LocalizeInfo>
      <Key>ValueOf</Key>
      <Value>The value of</Value>
      <Comment>Outline</Comment>
      <Link />
      <FontSize>12</FontSize>
      <FontName>Meiryo</FontName>
      <MaxNumber>12</MaxNumber>
    </LocalizeInfo>


     <LocalizeInfo>
      <Key>OutofRange</Key>
      <Value>is out of the range. It will be set within this limitation</Value>
      <Comment>Outline</Comment>
      <Link />
      <FontSize>12</FontSize>
      <FontName>Meiryo</FontName>
      <MaxNumber>12</MaxNumber>
    </LocalizeInfo>
    <LocalizeInfo>
      <Key>Width</Key>
      <Value>Largura</Value>
      <Comment>Stamp Width(Test Preview TextBox)</Comment>
      <Link />
      <FontSize>12</FontSize>
      <FontName>Segoe UI</FontName>
      <MaxNumber>12</MaxNumber>
    </LocalizeInfo>
    <LocalizeInfo>
      <Key>Date</Key>
      <Value>Data</Value>
      <Comment>Stamp Width(Test Preview TextBox)</Comment>
      <Link />
      <FontSize>12</FontSize>
      <FontName>Segoe UI</FontName>
      <MaxNumber>12</MaxNumber>
    </LocalizeInfo>
    <LocalizeInfo>
      <Key>Month</Key>
      <Value>Mês</Value>
      <Comment>Stamp Width(Test Preview TextBox)</Comment>
      <Link />
      <FontSize>12</FontSize>
      <FontName>Segoe UI</FontName>
      <MaxNumber>12</MaxNumber>
    </LocalizeInfo>
    <LocalizeInfo>
      <Key>Year</Key>
      <Value>Ano</Value>
      <Comment>Stamp Width(Test Preview TextBox)</Comment>
      <Link />
      <FontSize>12</FontSize>
      <FontName>Segoe UI</FontName>
      <MaxNumber>12</MaxNumber>
    </LocalizeInfo>
    <LocalizeInfo>
      <Key>DA010oo</Key>
      <Value />
      <Comment />
      <Link />
      <FontSize>12</FontSize>
      <FontName>Segoe UI</FontName>
      <MaxNumber>12</MaxNumber>
    </LocalizeInfo>
    <LocalizeInfo>
      <Key>DA011@</Key>
      <Value>H</Value>
      <Comment>Stamp Width(Test Preview TextBox)</Comment>
      <Link />
      <FontSize>12</FontSize>
      <FontName>Segoe UI</FontName>
      <MaxNumber>12</MaxNumber>
    </LocalizeInfo>
    <LocalizeInfo>
      <Key>Hour</Key>
      <Value>Hora</Value>
      <Comment>Stamp Width(Test Preview TextBox)</Comment>
      <Link />
      <FontSize>12</FontSize>
      <FontName>Segoe UI</FontName>
      <MaxNumber>12</MaxNumber>
    </LocalizeInfo>
    <LocalizeInfo>
      <Key>Minutes</Key>
      <Value>Minuto</Value>
      <Comment>Stamp Width(Test Preview TextBox)</Comment>
      <Link />
      <FontSize>12</FontSize>
      <FontName>Segoe UI</FontName>
      <MaxNumber>12</MaxNumber>
    </LocalizeInfo>
    <LocalizeInfo>
      <Key>Seconds</Key>
      <Value>Segundo</Value>
      <Comment>Stamp Width(Test Preview TextBox)</Comment>
      <Link />
      <FontSize>12</FontSize>
      <FontName>Segoe UI</FontName>
      <MaxNumber>12</MaxNumber>
    </LocalizeInfo>
    <LocalizeInfo>
      <Key>AM</Key>
      <Value>AM</Value>
      <Comment>Stamp Width(Test Preview TextBox)</Comment>
      <Link />
      <FontSize>12</FontSize>
      <FontName>Segoe UI</FontName>
      <MaxNumber>12</MaxNumber>
    </LocalizeInfo>
    <LocalizeInfo>
      <Key>PM</Key>
      <Value>PM</Value>
      <Comment>Stamp Width(Test Preview TextBox)</Comment>
      <Link />
      <FontSize>12</FontSize>
      <FontName>Segoe UI</FontName>
      <MaxNumber>12</MaxNumber>
    </LocalizeInfo>
    <LocalizeInfo>
      <Key>Filename</Key>
      <Value />
      <Comment>File Name : nmprint p1.ini</Comment>
      <Link />
      <FontSize>12</FontSize>
      <FontName>Segoe UI</FontName>
      <MaxNumber>12</MaxNumber>
    </LocalizeInfo>
    <LocalizeInfo>
      <Key>BackgroundDensity</Key>
      <Value>Densidade de fundo [%]</Value>
      <Comment>Background Density [%]</Comment>
      <Link />
      <FontSize>12</FontSize>
      <FontName>Segoe UI</FontName>
      <MaxNumber>12</MaxNumber>
    </LocalizeInfo>
    <LocalizeInfo>
      <Key>CharacterDensity</Key>
      <Value>Densidade de caracter [%]</Value>
      <Comment>Character Density [%]</Comment>
      <Link />
      <FontSize>12</FontSize>
      <FontName>Segoe UI</FontName>
      <MaxNumber>12</MaxNumber>
    </LocalizeInfo>
    <LocalizeInfo>
      <Key>Offset</Key>
      <Value>Desvio</Value>
      <Comment>Offset</Comment>
      <Link />
      <FontSize>12</FontSize>
      <FontName>Segoe UI</FontName>
      <MaxNumber>12</MaxNumber>
    </LocalizeInfo>
    <LocalizeInfo>
      <Key>Position</Key>
      <Value>Posição</Value>
      <Comment>Position</Comment>
      <Link />
      <FontSize>12</FontSize>
      <FontName>Segoe UI</FontName>
      <MaxNumber>12</MaxNumber>
    </LocalizeInfo>
    <LocalizeInfo>
      <Key>Enable</Key>
      <Value>Ativar</Value>
      <Comment>Enable</Comment>
      <Link />
      <FontSize>12</FontSize>
      <FontName>Segoe UI</FontName>
      <MaxNumber>12</MaxNumber>
    </LocalizeInfo>
    <LocalizeInfo>
      <Key>Xmm</Key>
      <Value>X [mm]</Value>
      <Comment>X[mm]</Comment>
      <Link />
      <FontSize>12</FontSize>
      <FontName>Segoe UI</FontName>
      <MaxNumber>12</MaxNumber>
    </LocalizeInfo>
    <LocalizeInfo>
      <Key>Ymm</Key>
      <Value>Y [mm]</Value>
      <Comment>Y[mm]</Comment>
      <Link />
      <FontSize>12</FontSize>
      <FontName>Segoe UI</FontName>
      <MaxNumber>12</MaxNumber>
    </LocalizeInfo>
    <LocalizeInfo>
      <Key>UpperLeft</Key>
      <Value>Superior esquerdo</Value>
      <Comment>Upper-Left</Comment>
      <Link />
      <FontSize>12</FontSize>
      <FontName>Segoe UI</FontName>
      <MaxNumber>12</MaxNumber>
    </LocalizeInfo>
    <LocalizeInfo>
      <Key>UpperCenter</Key>
      <Value>Superior centro</Value>
      <Comment>Upper-Center</Comment>
      <Link />
      <FontSize>12</FontSize>
      <FontName>Segoe UI</FontName>
      <MaxNumber>12</MaxNumber>
    </LocalizeInfo>
    <LocalizeInfo>
      <Key>UpperRight</Key>
      <Value>Superior direito</Value>
      <Comment>Upper-Right</Comment>
      <Link />
      <FontSize>12</FontSize>
      <FontName>Segoe UI</FontName>
      <MaxNumber>12</MaxNumber>
    </LocalizeInfo>
    <LocalizeInfo>
      <Key>Left</Key>
      <Value>Esquerda</Value>
      <Comment>Left</Comment>
      <Link />
      <FontSize>12</FontSize>
      <FontName>Segoe UI</FontName>
      <MaxNumber>12</MaxNumber>
    </LocalizeInfo>
    <LocalizeInfo>
      <Key>Right</Key>
      <Value>Direita</Value>
      <Comment>Right</Comment>
      <Link />
      <FontSize>12</FontSize>
      <FontName>Segoe UI</FontName>
      <MaxNumber>12</MaxNumber>
    </LocalizeInfo>
    <LocalizeInfo>
      <Key>LowerLeft</Key>
      <Value>Inferior esquerdo</Value>
      <Comment>Lower-Left</Comment>
      <Link />
      <FontSize>12</FontSize>
      <FontName>Segoe UI</FontName>
      <MaxNumber>12</MaxNumber>
    </LocalizeInfo>
    <LocalizeInfo>
      <Key>LowerCenter</Key>
      <Value>Inferior centro</Value>
      <Comment>Lower-Center</Comment>
      <Link />
      <FontSize>12</FontSize>
      <FontName>Segoe UI</FontName>
      <MaxNumber>12</MaxNumber>
    </LocalizeInfo>
    <LocalizeInfo>
      <Key>LowerRight</Key>
      <Value>Inferior direito</Value>
      <Comment>Lower-Right</Comment>
      <Link />
      <FontSize>12</FontSize>
      <FontName>Segoe UI</FontName>
      <MaxNumber>12</MaxNumber>
    </LocalizeInfo>
    <LocalizeInfo>
      <Key>Refresh</Key>
      <Value>Refrescar</Value>
      <Comment>Refresh</Comment>
      <Link />
      <FontSize>12</FontSize>
      <FontName>Segoe UI</FontName>
      <MaxNumber>12</MaxNumber>
    </LocalizeInfo>
    <LocalizeInfo>
      <Key>Preview</Key>
      <Value>Previsualização</Value>
      <Comment>Preview</Comment>
      <Link />
      <FontSize>12</FontSize>
      <FontName>Segoe UI</FontName>
      <MaxNumber>12</MaxNumber>
    </LocalizeInfo>
    <LocalizeInfo>
      <Key>StampSettings</Key>
      <Value>Ajustes de selo</Value>
      <Comment>Stamp Settings</Comment>
      <Link />
      <FontSize>12</FontSize>
      <FontName>Segoe UI</FontName>
      <MaxNumber>12</MaxNumber>
    </LocalizeInfo>
    <LocalizeInfo>
      <Key>SNo</Key>
      <Value>Não.</Value>
      <Comment>S.No</Comment>
      <Link />
      <FontSize>12</FontSize>
      <FontName>Segoe UI</FontName>
      <MaxNumber>12</MaxNumber>
    </LocalizeInfo>
    <LocalizeInfo>
      <Key>Edit</Key>
      <Value>Editar...</Value>
      <Comment>Edit...</Comment>
      <Link />
      <FontSize>12</FontSize>
      <FontName>Segoe UI</FontName>
      <MaxNumber>12</MaxNumber>
    </LocalizeInfo>
    <LocalizeInfo>
      <Key>Copy</Key>
      <Value>Copiar...</Value>
      <Comment>Copy...</Comment>
      <Link />
      <FontSize>12</FontSize>
      <FontName>Segoe UI</FontName>
      <MaxNumber>12</MaxNumber>
    </LocalizeInfo>
    <LocalizeInfo>
      <Key>Stamp1</Key>
      <Value>Selo 1</Value>
      <Comment>Stamp 1</Comment>
      <Link />
      <FontSize>12</FontSize>
      <FontName>Segoe UI</FontName>
      <MaxNumber>12</MaxNumber>
    </LocalizeInfo>
    <LocalizeInfo>
      <Key>Stamp2</Key>
      <Value>Selo 2</Value>
      <Comment>Stamp 2</Comment>
      <Link />
      <FontSize>12</FontSize>
      <FontName>Segoe UI</FontName>
      <MaxNumber>12</MaxNumber>
    </LocalizeInfo>
    <LocalizeInfo>
      <Key>Stamp3</Key>
      <Value>Selo 3</Value>
      <Comment>Stamp 3</Comment>
      <Link />
      <FontSize>12</FontSize>
      <FontName>Segoe UI</FontName>
      <MaxNumber>12</MaxNumber>
    </LocalizeInfo>
    <LocalizeInfo>
      <Key>Stamp4</Key>
      <Value>Selo 4</Value>
      <Comment>Stamp 4</Comment>
      <Link />
      <FontSize>12</FontSize>
      <FontName>Segoe UI</FontName>
      <MaxNumber>12</MaxNumber>
    </LocalizeInfo>
    <LocalizeInfo>
      <Key>Stamp5</Key>
      <Value>Selo 5</Value>
      <Comment>Stamp 5</Comment>
      <Link />
      <FontSize>12</FontSize>
      <FontName>Segoe UI</FontName>
      <MaxNumber>12</MaxNumber>
    </LocalizeInfo>
    <LocalizeInfo>
      <Key>Stamp6</Key>
      <Value>Selo 6</Value>
      <Comment>Stamp 6</Comment>
      <Link />
      <FontSize>12</FontSize>
      <FontName>Segoe UI</FontName>
      <MaxNumber>12</MaxNumber>
    </LocalizeInfo>
    <LocalizeInfo>
      <Key>Stamp7</Key>
      <Value>Selo 7</Value>
      <Comment>Stamp 7</Comment>
      <Link />
      <FontSize>12</FontSize>
      <FontName>Segoe UI</FontName>
      <MaxNumber>12</MaxNumber>
    </LocalizeInfo>
    <LocalizeInfo>
      <Key>Stamp8</Key>
      <Value>Selo 8</Value>
      <Comment>Stamp 8</Comment>
      <Link />
      <FontSize>12</FontSize>
      <FontName>Segoe UI</FontName>
      <MaxNumber>12</MaxNumber>
    </LocalizeInfo>
    <LocalizeInfo>
      <Key>Stamp9</Key>
      <Value>Selo 9</Value>
      <Comment>Stamp 9</Comment>
      <Link />
      <FontSize>12</FontSize>
      <FontName>Segoe UI</FontName>
      <MaxNumber>12</MaxNumber>
    </LocalizeInfo>
    <LocalizeInfo>
      <Key>Stamp10</Key>
      <Value>Selo 10</Value>
      <Comment>Stamp 10</Comment>
      <Link />
      <FontSize>12</FontSize>
      <FontName>Segoe UI</FontName>
      <MaxNumber>12</MaxNumber>
    </LocalizeInfo>
    <LocalizeInfo>
      <Key>OK</Key>
      <Value>OK</Value>
      <Comment>OK</Comment>
      <Link />
      <FontSize>12</FontSize>
      <FontName>Segoe UI</FontName>
      <MaxNumber>12</MaxNumber>
    </LocalizeInfo>
    <LocalizeInfo>
      <Key>Cancel</Key>
      <Value>Cancelar</Value>
      <Comment>Cancel</Comment>
      <Link />
      <FontSize>12</FontSize>
      <FontName>Segoe UI</FontName>
      <MaxNumber>12</MaxNumber>
    </LocalizeInfo>
    <LocalizeInfo>
      <Key>Prefix</Key>
      <Value>Prefixo</Value>
      <Comment>Prefix</Comment>
      <Link />
      <FontSize>12</FontSize>
      <FontName>Segoe UI</FontName>
      <MaxNumber>12</MaxNumber>
    </LocalizeInfo>
    <LocalizeInfo>
      <Key>Suffix</Key>
      <Value>Sufixo</Value>
      <Comment>Suffix</Comment>
      <Link />
      <FontSize>12</FontSize>
      <FontName>Segoe UI</FontName>
      <MaxNumber>12</MaxNumber>
    </LocalizeInfo>
    <LocalizeInfo>
      <Key>Sample</Key>
      <Value>Amostra</Value>
      <Comment>Sample</Comment>
      <Link />
      <FontSize>12</FontSize>
      <FontName>Segoe UI</FontName>
      <MaxNumber>12</MaxNumber>
    </LocalizeInfo>
    <LocalizeInfo>
      <Key>Alignment</Key>
      <Value>Alinhamento</Value>
      <Comment>Alignment</Comment>
      <Link />
      <FontSize>12</FontSize>
      <FontName>Segoe UI</FontName>
      <MaxNumber>12</MaxNumber>
    </LocalizeInfo>
    <LocalizeInfo>
      <Key>Contents</Key>
      <Value>Conteúdo</Value>
      <Comment>Contents</Comment>
      <Link />
      <FontSize>12</FontSize>
      <FontName>Segoe UI</FontName>
      <MaxNumber>12</MaxNumber>
    </LocalizeInfo>
    <LocalizeInfo>
      <Key>Item</Key>
      <Value>Item</Value>
      <Comment>Item</Comment>
      <Link />
      <FontSize>12</FontSize>
      <FontName>Segoe UI</FontName>
      <MaxNumber>12</MaxNumber>
    </LocalizeInfo>
    <LocalizeInfo>
      <Key>Line</Key>
      <Value>Linha</Value>
      <Comment>Line</Comment>
      <Link />
      <FontSize>12</FontSize>
      <FontName>Segoe UI</FontName>
      <MaxNumber>12</MaxNumber>
    </LocalizeInfo>
    <LocalizeInfo>
      <Key>Lengths</Key>
      <Value>Comprimento</Value>
      <Comment>Length</Comment>
      <Link />
      <FontSize>12</FontSize>
      <FontName>Segoe UI</FontName>
      <MaxNumber>12</MaxNumber>
    </LocalizeInfo>
    <LocalizeInfo>
      <Key>Options</Key>
      <Value>Opções</Value>
      <Comment>Options</Comment>
      <Link />
      <FontSize>12</FontSize>
      <FontName>Segoe UI</FontName>
      <MaxNumber>12</MaxNumber>
    </LocalizeInfo>
    <LocalizeInfo>
      <Key>StampNumber</Key>
      <Value />
      <Comment>Stamp Number : Printer - Stamp 1</Comment>
      <Link />
      <FontSize>12</FontSize>
      <FontName>Segoe UI</FontName>
      <MaxNumber>12</MaxNumber>
    </LocalizeInfo>
    <LocalizeInfo>
      <Key>GeneralSettings</Key>
      <Value>Configurações gerais</Value>
      <Comment>General Settings</Comment>
      <Link />
      <FontSize>12</FontSize>
      <FontName>Segoe UI</FontName>
      <MaxNumber>12</MaxNumber>
    </LocalizeInfo>
    <LocalizeInfo>
      <Key>Parameter</Key>
      <Value>Parâmetro</Value>
      <Comment>Parameter</Comment>
      <Link />
      <FontSize>12</FontSize>
      <FontName>Segoe UI</FontName>
      <MaxNumber>12</MaxNumber>
    </LocalizeInfo>
    <LocalizeInfo>
      <Key>Values</Key>
      <Value>Valor</Value>
      <Comment>Value</Comment>
      <Link />
      <FontSize>12</FontSize>
      <FontName>Segoe UI</FontName>
      <MaxNumber>12</MaxNumber>
    </LocalizeInfo>
    <LocalizeInfo>
      <Key>TotalLines</Key>
      <Value>Total de linhas ( 1 - 6 )</Value>
      <Comment>Total Lines ( 1 - 6 )</Comment>
      <Link />
      <FontSize>12</FontSize>
      <FontName>Segoe UI</FontName>
      <MaxNumber>12</MaxNumber>
    </LocalizeInfo>
    <LocalizeInfo>
      <Key>Default</Key>
      <Value>Esquerda justificado</Value>
      <Comment>Default Alignment in Stamp Edit model</Comment>
      <Link />
      <FontSize>12</FontSize>
      <FontName>Segoe UI</FontName>
      <MaxNumber>12</MaxNumber>
    </LocalizeInfo>
    <LocalizeInfo>
      <Key>Center</Key>
      <Value>Centrado</Value>
      <Comment>center alignemnt key in Stamp Edit Model</Comment>
      <Link />
      <FontSize>12</FontSize>
      <FontName>Segoe UI</FontName>
      <MaxNumber>12</MaxNumber>
    </LocalizeInfo>
    <LocalizeInfo>
      <Key>FontSizeText</Key>
      <Value>Tamanho da letra</Value>
      <Comment />
      <Link />
      <FontSize>12</FontSize>
      <FontName>Segoe UI</FontName>
      <MaxNumber>12</MaxNumber>
    </LocalizeInfo>
    <LocalizeInfo>
      <Key>FisrtLineFontSize</Key>
      <Value>1º</Value>
      <Comment />
      <Link />
      <FontSize>12</FontSize>
      <FontName>Segoe UI</FontName>
      <MaxNumber>12</MaxNumber>
    </LocalizeInfo>
    <LocalizeInfo>
      <Key>SecondLineFontSize</Key>
      <Value>2º</Value>
      <Comment />
      <Link />
      <FontSize>12</FontSize>
      <FontName>Segoe UI</FontName>
      <MaxNumber>12</MaxNumber>
    </LocalizeInfo>
    <LocalizeInfo>
      <Key>ThirdLineFontSize</Key>
      <Value>3º</Value>
      <Comment />
      <Link />
      <FontSize>12</FontSize>
      <FontName>Segoe UI</FontName>
      <MaxNumber>12</MaxNumber>
    </LocalizeInfo>
    <LocalizeInfo>
      <Key>ForthLineFontSize</Key>
      <Value>4º</Value>
      <Comment />
      <Link />
      <FontSize>12</FontSize>
      <FontName>Segoe UI</FontName>
      <MaxNumber>12</MaxNumber>
    </LocalizeInfo>
    <LocalizeInfo>
      <Key>FifthLineFontSize</Key>
      <Value>5º</Value>
      <Comment />
      <Link />
      <FontSize>12</FontSize>
      <FontName>Segoe UI</FontName>
      <MaxNumber>12</MaxNumber>
    </LocalizeInfo>
    <LocalizeInfo>
      <Key>SixthLineFontSize</Key>
      <Value>6º</Value>
      <Comment />
      <Link />
      <FontSize>12</FontSize>
      <FontName>Segoe UI</FontName>
      <MaxNumber>12</MaxNumber>
    </LocalizeInfo>
    <LocalizeInfo>
      <Key>LineNumber</Key>
      <Value>NúmeroLinha</Value>
      <Comment />
      <Link />
      <FontSize>12</FontSize>
      <FontName>Segoe UI</FontName>
      <MaxNumber>12</MaxNumber>
    </LocalizeInfo>
    <LocalizeInfo>
      <Key>Value</Key>
      <Value>Valor</Value>
      <Comment />
      <Link />
      <FontSize>12</FontSize>
      <FontName>Segoe UI</FontName>
      <MaxNumber>12</MaxNumber>
    </LocalizeInfo>
    <LocalizeInfo>
      <Key>StampId_undefined</Key>
      <Value>Indefinida</Value>
      <Comment />
      <Link />
      <FontSize>12</FontSize>
      <FontName>Segoe UI</FontName>
      <MaxNumber>12</MaxNumber>
    </LocalizeInfo>
    <LocalizeInfo>
      <Key>StampId_GPPS0069</Key>
      <Value>Data do estudo</Value>
      <Comment />
      <Link />
      <FontSize>12</FontSize>
      <FontName>Segoe UI</FontName>
      <MaxNumber>12</MaxNumber>
    </LocalizeInfo>
    <LocalizeInfo>
      <Key>StampId_00080023</Key>
      <Value>Data da imagem</Value>
      <Comment />
      <Link />
      <FontSize>12</FontSize>
      <FontName>Segoe UI</FontName>
      <MaxNumber>12</MaxNumber>
    </LocalizeInfo>
    <LocalizeInfo>
      <Key>StampId_GPPS0070</Key>
      <Value>Hora do estudo</Value>
      <Comment />
      <Link />
      <FontSize>12</FontSize>
      <FontName>Segoe UI</FontName>
      <MaxNumber>12</MaxNumber>
    </LocalizeInfo>
    <LocalizeInfo>
      <Key>StampId_00080033</Key>
      <Value>Hora da imagem</Value>
      <Comment />
      <Link />
      <FontSize>12</FontSize>
      <FontName>Segoe UI</FontName>
      <MaxNumber>12</MaxNumber>
    </LocalizeInfo>
    <LocalizeInfo>
      <Key>StampId_GPPS0095</Key>
      <Value>Número de adesão</Value>
      <Comment />
      <Link />
      <FontSize>12</FontSize>
      <FontName>Segoe UI</FontName>
      <MaxNumber>12</MaxNumber>
    </LocalizeInfo>
    <LocalizeInfo>
      <Key>StampId_00080080</Key>
      <Value>Nome da instituição</Value>
      <Comment />
      <Link />
      <FontSize>12</FontSize>
      <FontName>Segoe UI</FontName>
      <MaxNumber>12</MaxNumber>
    </LocalizeInfo>
    <LocalizeInfo>
      <Key>StampId_00080081</Key>
      <Value>Endereço da instituição</Value>
      <Comment />
      <Link />
      <FontSize>12</FontSize>
      <FontName>Segoe UI</FontName>
      <MaxNumber>12</MaxNumber>
    </LocalizeInfo>
    <LocalizeInfo>
      <Key>StampId_GPPS0043</Key>
      <Value>Médico assistente</Value>
      <Comment />
      <Link />
      <FontSize>12</FontSize>
      <FontName>Segoe UI</FontName>
      <MaxNumber>12</MaxNumber>
    </LocalizeInfo>
    <LocalizeInfo>
      <Key>StampId_GPPS0044</Key>
      <Value />
      <Comment />
      <Link />
      <FontSize>12</FontSize>
      <FontName>Segoe UI</FontName>
      <MaxNumber>12</MaxNumber>
    </LocalizeInfo>
    <LocalizeInfo>
      <Key>StampId_GPPS0045</Key>
      <Value />
      <Comment />
      <Link />
      <FontSize>12</FontSize>
      <FontName>Segoe UI</FontName>
      <MaxNumber>12</MaxNumber>
    </LocalizeInfo>
    <LocalizeInfo>
      <Key>StampId_00081010</Key>
      <Value>Nome da estação</Value>
      <Comment />
      <Link />
      <FontSize>12</FontSize>
      <FontName>Segoe UI</FontName>
      <MaxNumber>12</MaxNumber>
    </LocalizeInfo>
    <LocalizeInfo>
      <Key>StampId_00081040</Key>
      <Value>Nome do departamento</Value>
      <Comment />
      <Link />
      <FontSize>12</FontSize>
      <FontName>Segoe UI</FontName>
      <MaxNumber>12</MaxNumber>
    </LocalizeInfo>
    <LocalizeInfo>
      <Key>StampId_GPPS0046</Key>
      <Value>Médico de registo</Value>
      <Comment />
      <Link />
      <FontSize>12</FontSize>
      <FontName>Segoe UI</FontName>
      <MaxNumber>12</MaxNumber>
    </LocalizeInfo>
    <LocalizeInfo>
      <Key>StampId_GPPS0047</Key>
      <Value />
      <Comment />
      <Link />
      <FontSize>12</FontSize>
      <FontName>Segoe UI</FontName>
      <MaxNumber>12</MaxNumber>
    </LocalizeInfo>
    <LocalizeInfo>
      <Key>StampId_GPPS0048</Key>
      <Value />
      <Comment />
      <Link />
      <FontSize>12</FontSize>
      <FontName>Segoe UI</FontName>
      <MaxNumber>12</MaxNumber>
    </LocalizeInfo>
    <LocalizeInfo>
      <Key>StampId_GPSE0015</Key>
      <Value>Médico executante</Value>
      <Comment />
      <Link />
      <FontSize>12</FontSize>
      <FontName>Segoe UI</FontName>
      <MaxNumber>12</MaxNumber>
    </LocalizeInfo>
    <LocalizeInfo>
      <Key>StampId_GPSE0016</Key>
      <Value />
      <Comment />
      <Link />
      <FontSize>12</FontSize>
      <FontName>Segoe UI</FontName>
      <MaxNumber>12</MaxNumber>
    </LocalizeInfo>
    <LocalizeInfo>
      <Key>StampId_GPSE0017</Key>
      <Value />
      <Comment />
      <Link />
      <FontSize>12</FontSize>
      <FontName>Segoe UI</FontName>
      <MaxNumber>12</MaxNumber>
    </LocalizeInfo>
    <LocalizeInfo>
      <Key>StampId_GPPS0049</Key>
      <Value>Médico para leitura do estudo</Value>
      <Comment />
      <Link />
      <FontSize>12</FontSize>
      <FontName>Segoe UI</FontName>
      <MaxNumber>12</MaxNumber>
    </LocalizeInfo>
    <LocalizeInfo>
      <Key>StampId_GPPS0050</Key>
      <Value>Nome do operador</Value>
      <Comment />
      <Link />
      <FontSize>12</FontSize>
      <FontName>Segoe UI</FontName>
      <MaxNumber>12</MaxNumber>
    </LocalizeInfo>
    <LocalizeInfo>
      <Key>StampId_GPPS0051</Key>
      <Value />
      <Comment />
      <Link />
      <FontSize>12</FontSize>
      <FontName>Segoe UI</FontName>
      <MaxNumber>12</MaxNumber>
    </LocalizeInfo>
    <LocalizeInfo>
      <Key>StampId_GPSE0012</Key>
      <Value>Nome do operador</Value>
      <Comment />
      <Link />
      <FontSize>12</FontSize>
      <FontName>Segoe UI</FontName>
      <MaxNumber>12</MaxNumber>
    </LocalizeInfo>
    <LocalizeInfo>
      <Key>StampId_GPSE0013</Key>
      <Value />
      <Comment />
      <Link />
      <FontSize>12</FontSize>
      <FontName>Segoe UI</FontName>
      <MaxNumber>12</MaxNumber>
    </LocalizeInfo>
    <LocalizeInfo>
      <Key>StampId_GPSE0014</Key>
      <Value />
      <Comment />
      <Link />
      <FontSize>12</FontSize>
      <FontName>Segoe UI</FontName>
      <MaxNumber>12</MaxNumber>
    </LocalizeInfo>
    <LocalizeInfo>
      <Key>StampId_GPPS0052</Key>
      <Value>DescriçãoDiagnóstico</Value>
      <Comment />
      <Link />
      <FontSize>12</FontSize>
      <FontName>Segoe UI</FontName>
      <MaxNumber>12</MaxNumber>
    </LocalizeInfo>
    <LocalizeInfo>
      <Key>StampId_00081090</Key>
      <Value>Nome do modelo</Value>
      <Comment />
      <Link />
      <FontSize>12</FontSize>
      <FontName>Segoe UI</FontName>
      <MaxNumber>12</MaxNumber>
    </LocalizeInfo>
    <LocalizeInfo>
      <Key>StampId_GPPS0033</Key>
      <Value>Nome do paciente</Value>
      <Comment />
      <Link />
      <FontSize>12</FontSize>
      <FontName>Segoe UI</FontName>
      <MaxNumber>12</MaxNumber>
    </LocalizeInfo>
    <LocalizeInfo>
      <Key>StampId_GPPS0034</Key>
      <Value />
      <Comment />
      <Link />
      <FontSize>12</FontSize>
      <FontName>Segoe UI</FontName>
      <MaxNumber>12</MaxNumber>
    </LocalizeInfo>
    <LocalizeInfo>
      <Key>StampId_GPPS0035</Key>
      <Value />
      <Comment />
      <Link />
      <FontSize>12</FontSize>
      <FontName>Segoe UI</FontName>
      <MaxNumber>12</MaxNumber>
    </LocalizeInfo>
    <LocalizeInfo>
      <Key>StampId_GPPS0032</Key>
      <Value>ID do paciente</Value>
      <Comment />
      <Link />
      <FontSize>12</FontSize>
      <FontName>Segoe UI</FontName>
      <MaxNumber>12</MaxNumber>
    </LocalizeInfo>
    <LocalizeInfo>
      <Key>StampId_GPPS0036</Key>
      <Value>Data de nascimento do paciente</Value>
      <Comment />
      <Link />
      <FontSize>12</FontSize>
      <FontName>Segoe UI</FontName>
      <MaxNumber>12</MaxNumber>
    </LocalizeInfo>
    <LocalizeInfo>
      <Key>StampId_GPPS0037</Key>
      <Value>Hora de nascimento do paciente</Value>
      <Comment />
      <Link />
      <FontSize>12</FontSize>
      <FontName>Segoe UI</FontName>
      <MaxNumber>12</MaxNumber>
    </LocalizeInfo>
    <LocalizeInfo>
      <Key>StampId_GPPS0038</Key>
      <Value>Sexo do paciente</Value>
      <Comment />
      <Link />
      <FontSize>12</FontSize>
      <FontName>Segoe UI</FontName>
      <MaxNumber>12</MaxNumber>
    </LocalizeInfo>
    <LocalizeInfo>
      <Key>StampId_GPPS0081</Key>
      <Value>ID de outro paciente</Value>
      <Comment />
      <Link />
      <FontSize>12</FontSize>
      <FontName>Segoe UI</FontName>
      <MaxNumber>12</MaxNumber>
    </LocalizeInfo>
    <LocalizeInfo>
      <Key>StampId_GPPS0082</Key>
      <Value>Outros nomes do paciente</Value>
      <Comment />
      <Link />
      <FontSize>12</FontSize>
      <FontName>Segoe UI</FontName>
      <MaxNumber>12</MaxNumber>
    </LocalizeInfo>
    <LocalizeInfo>
      <Key>StampId_GPPS0083</Key>
      <Value />
      <Comment />
      <Link />
      <FontSize>12</FontSize>
      <FontName>Segoe UI</FontName>
      <MaxNumber>12</MaxNumber>
    </LocalizeInfo>
    <LocalizeInfo>
      <Key>StampId_GPPS0084</Key>
      <Value />
      <Comment />
      <Link />
      <FontSize>12</FontSize>
      <FontName>Segoe UI</FontName>
      <MaxNumber>12</MaxNumber>
    </LocalizeInfo>
    <LocalizeInfo>
      <Key>StampId_GPPS0011</Key>
      <Value>Idade do paciente</Value>
      <Comment />
      <Link />
      <FontSize>12</FontSize>
      <FontName>Segoe UI</FontName>
      <MaxNumber>12</MaxNumber>
    </LocalizeInfo>
    <LocalizeInfo>
      <Key>StampId_GPPS0053</Key>
      <Value>Altura do paciente</Value>
      <Comment />
      <Link />
      <FontSize>12</FontSize>
      <FontName>Segoe UI</FontName>
      <MaxNumber>12</MaxNumber>
    </LocalizeInfo>
    <LocalizeInfo>
      <Key>StampId_GPPS0054</Key>
      <Value>Peso do paciente</Value>
      <Comment />
      <Link />
      <FontSize>12</FontSize>
      <FontName>Segoe UI</FontName>
      <MaxNumber>12</MaxNumber>
    </LocalizeInfo>
    <LocalizeInfo>
      <Key>StampId_GPPS0058</Key>
      <Value>Alertas médicos</Value>
      <Comment />
      <Link />
      <FontSize>12</FontSize>
      <FontName>Segoe UI</FontName>
      <MaxNumber>12</MaxNumber>
    </LocalizeInfo>
    <LocalizeInfo>
      <Key>StampId_GPPS0059</Key>
      <Value>Alergias de contraste</Value>
      <Comment />
      <Link />
      <FontSize>12</FontSize>
      <FontName>Segoe UI</FontName>
      <MaxNumber>12</MaxNumber>
    </LocalizeInfo>
    <LocalizeInfo>
      <Key>StampId_GPPS0085</Key>
      <Value>Grupo étnico</Value>
      <Comment />
      <Link />
      <FontSize>12</FontSize>
      <FontName>Segoe UI</FontName>
      <MaxNumber>12</MaxNumber>
    </LocalizeInfo>
    <LocalizeInfo>
      <Key>StampId_GPPS0055</Key>
      <Value>Ocupação</Value>
      <Comment />
      <Link />
      <FontSize>12</FontSize>
      <FontName>Segoe UI</FontName>
      <MaxNumber>12</MaxNumber>
    </LocalizeInfo>
    <LocalizeInfo>
      <Key>StampId_GPPS0061</Key>
      <Value>Adicionar histórico do paciente</Value>
      <Comment />
      <Link />
      <FontSize>12</FontSize>
      <FontName>Segoe UI</FontName>
      <MaxNumber>12</MaxNumber>
    </LocalizeInfo>
    <LocalizeInfo>
      <Key>StampId_GPPS0062</Key>
      <Value>Estado de gravidez</Value>
      <Comment />
      <Link />
      <FontSize>12</FontSize>
      <FontName>Segoe UI</FontName>
      <MaxNumber>12</MaxNumber>
    </LocalizeInfo>
    <LocalizeInfo>
      <Key>StampId_GPPS0039</Key>
      <Value>Comentários do paciente</Value>
      <Comment />
      <Link />
      <FontSize>12</FontSize>
      <FontName>Segoe UI</FontName>
      <MaxNumber>12</MaxNumber>
    </LocalizeInfo>
    <LocalizeInfo>
      <Key>StampId_00180010:0</Key>
      <Value>Agente de contraste/bolo</Value>
      <Comment />
      <Link />
      <FontSize>12</FontSize>
      <FontName>Segoe UI</FontName>
      <MaxNumber>12</MaxNumber>
    </LocalizeInfo>
    <LocalizeInfo>
      <Key>StampId_GEIM0021</Key>
      <Value>Parte do corpo examinada</Value>
      <Comment />
      <Link />
      <FontSize>12</FontSize>
      <FontName>Segoe UI</FontName>
      <MaxNumber>12</MaxNumber>
    </LocalizeInfo>
    <LocalizeInfo>
      <Key>StampId_00180060</Key>
      <Value>kVp</Value>
      <Comment />
      <Link />
      <FontSize>12</FontSize>
      <FontName>Segoe UI</FontName>
      <MaxNumber>12</MaxNumber>
    </LocalizeInfo>
    <LocalizeInfo>
      <Key>StampId_00181000</Key>
      <Value>Número de série</Value>
      <Comment />
      <Link />
      <FontSize>12</FontSize>
      <FontName>Segoe UI</FontName>
      <MaxNumber>12</MaxNumber>
    </LocalizeInfo>
    <LocalizeInfo>
      <Key>StampId_00181020:0</Key>
      <Value>Versões de software</Value>
      <Comment />
      <Link />
      <FontSize>12</FontSize>
      <FontName>Segoe UI</FontName>
      <MaxNumber>12</MaxNumber>
    </LocalizeInfo>
    <LocalizeInfo>
      <Key>StampId_00311107;00181040</Key>
      <Value>Rota C/B</Value>
      <Comment />
      <Link />
      <FontSize>12</FontSize>
      <FontName>Segoe UI</FontName>
      <MaxNumber>12</MaxNumber>
    </LocalizeInfo>
    <LocalizeInfo>
      <Key>StampId_00311107;00181041</Key>
      <Value>Volume C/B(cm3)</Value>
      <Comment />
      <Link />
      <FontSize>12</FontSize>
      <FontName>Segoe UI</FontName>
      <MaxNumber>12</MaxNumber>
    </LocalizeInfo>
    <LocalizeInfo>
      <Key>StampId_00311107;00181042</Key>
      <Value>Tempo de início C/B</Value>
      <Comment />
      <Link />
      <FontSize>12</FontSize>
      <FontName>Segoe UI</FontName>
      <MaxNumber>12</MaxNumber>
    </LocalizeInfo>
    <LocalizeInfo>
      <Key>StampId_00311107;00181043</Key>
      <Value>Tempo de fim C/B</Value>
      <Comment />
      <Link />
      <FontSize>12</FontSize>
      <FontName>Segoe UI</FontName>
      <MaxNumber>12</MaxNumber>
    </LocalizeInfo>
    <LocalizeInfo>
      <Key>StampId_00311107;00181044</Key>
      <Value>Dose total C/B</Value>
      <Comment />
      <Link />
      <FontSize>12</FontSize>
      <FontName>Segoe UI</FontName>
      <MaxNumber>12</MaxNumber>
    </LocalizeInfo>
    <LocalizeInfo>
      <Key>StampId_00311107;00181046</Key>
      <Value>Taxa de fluxo de contraste</Value>
      <Comment />
      <Link />
      <FontSize>12</FontSize>
      <FontName>Segoe UI</FontName>
      <MaxNumber>12</MaxNumber>
    </LocalizeInfo>
    <LocalizeInfo>
      <Key>StampId_00311107;00181047</Key>
      <Value>Duração do fluxo de contraste</Value>
      <Comment />
      <Link />
      <FontSize>12</FontSize>
      <FontName>Segoe UI</FontName>
      <MaxNumber>12</MaxNumber>
    </LocalizeInfo>
    <LocalizeInfo>
      <Key>StampId_00311107;00181048</Key>
      <Value>Ingrediente C/B</Value>
      <Comment />
      <Link />
      <FontSize>12</FontSize>
      <FontName>Segoe UI</FontName>
      <MaxNumber>12</MaxNumber>
    </LocalizeInfo>
    <LocalizeInfo>
      <Key>StampId_00311107;00181049</Key>
      <Value>Concentração C/B</Value>
      <Comment />
      <Link />
      <FontSize>12</FontSize>
      <FontName>Segoe UI</FontName>
      <MaxNumber>12</MaxNumber>
    </LocalizeInfo>
    <LocalizeInfo>
      <Key>StampId_00181110</Key>
      <Value>Detetor de origem[mm]</Value>
      <Comment />
      <Link />
      <FontSize>12</FontSize>
      <FontName>Segoe UI</FontName>
      <MaxNumber>12</MaxNumber>
    </LocalizeInfo>
    <LocalizeInfo>
      <Key>StampId_00181111</Key>
      <Value>Paciente de origem[mm]</Value>
      <Comment />
      <Link />
      <FontSize>12</FontSize>
      <FontName>Segoe UI</FontName>
      <MaxNumber>12</MaxNumber>
    </LocalizeInfo>
    <LocalizeInfo>
      <Key>StampId_00181114</Key>
      <Value>Mag. Fator(x100)</Value>
      <Comment />
      <Link />
      <FontSize>12</FontSize>
      <FontName>Segoe UI</FontName>
      <MaxNumber>12</MaxNumber>
    </LocalizeInfo>
    <LocalizeInfo>
      <Key>StampId_00181147</Key>
      <Value>Campo de forma de visualização</Value>
      <Comment />
      <Link />
      <FontSize>12</FontSize>
      <FontName>Segoe UI</FontName>
      <MaxNumber>12</MaxNumber>
    </LocalizeInfo>
    <LocalizeInfo>
      <Key>StampId_00181150</Key>
      <Value>Tempo de exposição</Value>
      <Comment />
      <Link />
      <FontSize>12</FontSize>
      <FontName>Segoe UI</FontName>
      <MaxNumber>12</MaxNumber>
    </LocalizeInfo>
    <LocalizeInfo>
      <Key>StampId_00181151</Key>
      <Value>Corrente do tubo de raio-X</Value>
      <Comment />
      <Link />
      <FontSize>12</FontSize>
      <FontName>Segoe UI</FontName>
      <MaxNumber>12</MaxNumber>
    </LocalizeInfo>
    <LocalizeInfo>
      <Key>StampId_00181152</Key>
      <Value>Exposição</Value>
      <Comment />
      <Link />
      <FontSize>12</FontSize>
      <FontName>Segoe UI</FontName>
      <MaxNumber>12</MaxNumber>
    </LocalizeInfo>
    <LocalizeInfo>
      <Key>StampId_00181156</Key>
      <Value>Tipo de retificação</Value>
      <Comment />
      <Link />
      <FontSize>12</FontSize>
      <FontName>Segoe UI</FontName>
      <MaxNumber>12</MaxNumber>
    </LocalizeInfo>
    <LocalizeInfo>
      <Key>StampId_0018115E</Key>
      <Value>Produção de dose da área de imagem</Value>
      <Comment />
      <Link />
      <FontSize>12</FontSize>
      <FontName>Segoe UI</FontName>
      <MaxNumber>12</MaxNumber>
    </LocalizeInfo>
    <LocalizeInfo>
      <Key>StampId_00181160</Key>
      <Value>Tipo de filtro</Value>
      <Comment />
      <Link />
      <FontSize>12</FontSize>
      <FontName>Segoe UI</FontName>
      <MaxNumber>12</MaxNumber>
    </LocalizeInfo>
    <LocalizeInfo>
      <Key>StampId_00181164:0</Key>
      <Value>Espaço de fila de pixel</Value>
      <Comment />
      <Link />
      <FontSize>12</FontSize>
      <FontName>Segoe UI</FontName>
      <MaxNumber>12</MaxNumber>
    </LocalizeInfo>
    <LocalizeInfo>
      <Key>StampId_00181164:1</Key>
      <Value>Espaço de coluna de pixel</Value>
      <Comment />
      <Link />
      <FontSize>12</FontSize>
      <FontName>Segoe UI</FontName>
      <MaxNumber>12</MaxNumber>
    </LocalizeInfo>
    <LocalizeInfo>
      <Key>StampId_00181166</Key>
      <Value>Grelha</Value>
      <Comment />
      <Link />
      <FontSize>12</FontSize>
      <FontName>Segoe UI</FontName>
      <MaxNumber>12</MaxNumber>
    </LocalizeInfo>
    <LocalizeInfo>
      <Key>StampId_00181190</Key>
      <Value>Ponto focal</Value>
      <Comment />
      <Link />
      <FontSize>12</FontSize>
      <FontName>Segoe UI</FontName>
      <MaxNumber>12</MaxNumber>
    </LocalizeInfo>
    <LocalizeInfo>
      <Key>StampId_00181191</Key>
      <Value>Material anodo</Value>
      <Comment />
      <Link />
      <FontSize>12</FontSize>
      <FontName>Segoe UI</FontName>
      <MaxNumber>12</MaxNumber>
    </LocalizeInfo>
    <LocalizeInfo>
      <Key>StampId_001811A0</Key>
      <Value>Espessura do peito</Value>
      <Comment />
      <Link />
      <FontSize>12</FontSize>
      <FontName>Segoe UI</FontName>
      <MaxNumber>12</MaxNumber>
    </LocalizeInfo>
    <LocalizeInfo>
      <Key>StampId_001811A2</Key>
      <Value>Pressão</Value>
      <Comment />
      <Link />
      <FontSize>12</FontSize>
      <FontName>Segoe UI</FontName>
      <MaxNumber>12</MaxNumber>
    </LocalizeInfo>
    <LocalizeInfo>
      <Key>StampId_00181004:0</Key>
      <Value>ID da placa</Value>
      <Comment />
      <Link />
      <FontSize>12</FontSize>
      <FontName>Segoe UI</FontName>
      <MaxNumber>12</MaxNumber>
    </LocalizeInfo>
    <LocalizeInfo>
      <Key>StampId_00181402</Key>
      <Value>Orientação da cassete</Value>
      <Comment />
      <Link />
      <FontSize>12</FontSize>
      <FontName>Segoe UI</FontName>
      <MaxNumber>12</MaxNumber>
    </LocalizeInfo>
    <LocalizeInfo>
      <Key>StampId_00181403</Key>
      <Value>Tamanho de leitura</Value>
      <Comment />
      <Link />
      <FontSize>12</FontSize>
      <FontName>Segoe UI</FontName>
      <MaxNumber>12</MaxNumber>
    </LocalizeInfo>
    <LocalizeInfo>
      <Key>StampId_00181510:0</Key>
      <Value>Detetor de ângulo primário</Value>
      <Comment />
      <Link />
      <FontSize>12</FontSize>
      <FontName>Segoe UI</FontName>
      <MaxNumber>12</MaxNumber>
    </LocalizeInfo>
    <LocalizeInfo>
      <Key>StampId_00185101:0</Key>
      <Value>Ver posição</Value>
      <Comment />
      <Link />
      <FontSize>12</FontSize>
      <FontName>Segoe UI</FontName>
      <MaxNumber>12</MaxNumber>
    </LocalizeInfo>
    <LocalizeInfo>
      <Key>StampId_00186000</Key>
      <Value>Sensibilidade</Value>
      <Comment />
      <Link />
      <FontSize>12</FontSize>
      <FontName>Segoe UI</FontName>
      <MaxNumber>12</MaxNumber>
    </LocalizeInfo>
    <LocalizeInfo>
      <Key>StampId_0018700A</Key>
      <Value>ID do detetor</Value>
      <Comment />
      <Link />
      <FontSize>12</FontSize>
      <FontName>Segoe UI</FontName>
      <MaxNumber>12</MaxNumber>
    </LocalizeInfo>
    <LocalizeInfo>
      <Key>StampId_00187040</Key>
      <Value>Material absor. da grelha</Value>
      <Comment />
      <Link />
      <FontSize>12</FontSize>
      <FontName>Segoe UI</FontName>
      <MaxNumber>12</MaxNumber>
    </LocalizeInfo>
    <LocalizeInfo>
      <Key>StampId_00187041</Key>
      <Value>Material espaço da grelha</Value>
      <Comment />
      <Link />
      <FontSize>12</FontSize>
      <FontName>Segoe UI</FontName>
      <MaxNumber>12</MaxNumber>
    </LocalizeInfo>
    <LocalizeInfo>
      <Key>StampId_00187042</Key>
      <Value>Espessura da grelha</Value>
      <Comment />
      <Link />
      <FontSize>12</FontSize>
      <FontName>Segoe UI</FontName>
      <MaxNumber>12</MaxNumber>
    </LocalizeInfo>
    <LocalizeInfo>
      <Key>StampId_00187044</Key>
      <Value>Nível da grelha</Value>
      <Comment />
      <Link />
      <FontSize>12</FontSize>
      <FontName>Segoe UI</FontName>
      <MaxNumber>12</MaxNumber>
    </LocalizeInfo>
    <LocalizeInfo>
      <Key>StampId_00187046:0</Key>
      <Value>Taxa de aspeto da grelha -V</Value>
      <Comment />
      <Link />
      <FontSize>12</FontSize>
      <FontName>Segoe UI</FontName>
      <MaxNumber>12</MaxNumber>
    </LocalizeInfo>
    <LocalizeInfo>
      <Key>StampId_00187046:1</Key>
      <Value>Taxa de aspeto da grelha -H</Value>
      <Comment />
      <Link />
      <FontSize>12</FontSize>
      <FontName>Segoe UI</FontName>
      <MaxNumber>12</MaxNumber>
    </LocalizeInfo>
    <LocalizeInfo>
      <Key>StampId_0018704C</Key>
      <Value>Distância focal da grelha</Value>
      <Comment />
      <Link />
      <FontSize>12</FontSize>
      <FontName>Segoe UI</FontName>
      <MaxNumber>12</MaxNumber>
    </LocalizeInfo>
    <LocalizeInfo>
      <Key>StampId_00187050</Key>
      <Value>Filtrar material </Value>
      <Comment />
      <Link />
      <FontSize>12</FontSize>
      <FontName>Segoe UI</FontName>
      <MaxNumber>12</MaxNumber>
    </LocalizeInfo>
    <LocalizeInfo>
      <Key>StampId_00187052</Key>
      <Value>Filtrar espessura min.</Value>
      <Comment />
      <Link />
      <FontSize>12</FontSize>
      <FontName>Segoe UI</FontName>
      <MaxNumber>12</MaxNumber>
    </LocalizeInfo>
    <LocalizeInfo>
      <Key>StampId_00187054</Key>
      <Value>Filtrar espessura máx.</Value>
      <Comment />
      <Link />
      <FontSize>12</FontSize>
      <FontName>Segoe UI</FontName>
      <MaxNumber>12</MaxNumber>
    </LocalizeInfo>
    <LocalizeInfo>
      <Key>StampId_00187060</Key>
      <Value>Modo de controlo de exposição</Value>
      <Comment />
      <Link />
      <FontSize>12</FontSize>
      <FontName>Segoe UI</FontName>
      <MaxNumber>12</MaxNumber>
    </LocalizeInfo>
    <LocalizeInfo>
      <Key>StampId_00187064</Key>
      <Value>Estado de exposição</Value>
      <Comment />
      <Link />
      <FontSize>12</FontSize>
      <FontName>Segoe UI</FontName>
      <MaxNumber>12</MaxNumber>
    </LocalizeInfo>
    <LocalizeInfo>
      <Key>StampId_GPPS0003</Key>
      <Value>Exemplo de estudo UID</Value>
      <Comment />
      <Link />
      <FontSize>12</FontSize>
      <FontName>Segoe UI</FontName>
      <MaxNumber>12</MaxNumber>
    </LocalizeInfo>
    <LocalizeInfo>
      <Key>StampId_GPSE0005</Key>
      <Value>Exemplo de série UID</Value>
      <Comment />
      <Link />
      <FontSize>12</FontSize>
      <FontName>Segoe UI</FontName>
      <MaxNumber>12</MaxNumber>
    </LocalizeInfo>
    <LocalizeInfo>
      <Key>StampId_GPPS0012</Key>
      <Value>ID do estudo</Value>
      <Comment />
      <Link />
      <FontSize>12</FontSize>
      <FontName>Segoe UI</FontName>
      <MaxNumber>12</MaxNumber>
    </LocalizeInfo>
    <LocalizeInfo>
      <Key>StampId_GPSE0006</Key>
      <Value>Número de série</Value>
      <Comment />
      <Link />
      <FontSize>12</FontSize>
      <FontName>Segoe UI</FontName>
      <MaxNumber>12</MaxNumber>
    </LocalizeInfo>
    <LocalizeInfo>
      <Key>StampId_00200013</Key>
      <Value>ID do exemplo</Value>
      <Comment />
      <Link />
      <FontSize>12</FontSize>
      <FontName>Segoe UI</FontName>
      <MaxNumber>12</MaxNumber>
    </LocalizeInfo>
    <LocalizeInfo>
      <Key>StampId_00200060:0</Key>
      <Value>Lateralidade</Value>
      <Comment />
      <Link />
      <FontSize>12</FontSize>
      <FontName>Segoe UI</FontName>
      <MaxNumber>12</MaxNumber>
    </LocalizeInfo>
    <LocalizeInfo>
      <Key>StampId_00200062:0</Key>
      <Value>Lateralidade da imagem</Value>
      <Comment />
      <Link />
      <FontSize>12</FontSize>
      <FontName>Segoe UI</FontName>
      <MaxNumber>12</MaxNumber>
    </LocalizeInfo>
    <LocalizeInfo>
      <Key>StampId_00204000</Key>
      <Value>Comentário da imagem</Value>
      <Comment />
      <Link />
      <FontSize>12</FontSize>
      <FontName>Segoe UI</FontName>
      <MaxNumber>12</MaxNumber>
    </LocalizeInfo>
    <LocalizeInfo>
      <Key>StampId_00280010</Key>
      <Value>Filas</Value>
      <Comment />
      <Link />
      <FontSize>12</FontSize>
      <FontName>Segoe UI</FontName>
      <MaxNumber>12</MaxNumber>
    </LocalizeInfo>
    <LocalizeInfo>
      <Key>StampId_00280011</Key>
      <Value>Colunas</Value>
      <Comment />
      <Link />
      <FontSize>12</FontSize>
      <FontName>Segoe UI</FontName>
      <MaxNumber>12</MaxNumber>
    </LocalizeInfo>
    <LocalizeInfo>
      <Key>StampId_00280300</Key>
      <Value>Imagem QC</Value>
      <Comment />
      <Link />
      <FontSize>12</FontSize>
      <FontName>Segoe UI</FontName>
      <MaxNumber>12</MaxNumber>
    </LocalizeInfo>
    <LocalizeInfo>
      <Key>StampId_GPPS0074</Key>
      <Value>Médico solicitante</Value>
      <Comment />
      <Link />
      <FontSize>12</FontSize>
      <FontName>Segoe UI</FontName>
      <MaxNumber>12</MaxNumber>
    </LocalizeInfo>
    <LocalizeInfo>
      <Key>StampId_GPPS0075</Key>
      <Value />
      <Comment />
      <Link />
      <FontSize>12</FontSize>
      <FontName>Segoe UI</FontName>
      <MaxNumber>12</MaxNumber>
    </LocalizeInfo>
    <LocalizeInfo>
      <Key>StampId_GPPS0076</Key>
      <Value />
      <Comment />
      <Link />
      <FontSize>12</FontSize>
      <FontName>Segoe UI</FontName>
      <MaxNumber>12</MaxNumber>
    </LocalizeInfo>
    <LocalizeInfo>
      <Key>StampId_GPPS0026</Key>
      <Value>Serviço de pedido</Value>
      <Comment />
      <Link />
      <FontSize>12</FontSize>
      <FontName>Segoe UI</FontName>
      <MaxNumber>12</MaxNumber>
    </LocalizeInfo>
    <LocalizeInfo>
      <Key>StampId_GPPS0096</Key>
      <Value>Comentários do estudo</Value>
      <Comment />
      <Link />
      <FontSize>12</FontSize>
      <FontName>Segoe UI</FontName>
      <MaxNumber>12</MaxNumber>
    </LocalizeInfo>
    <LocalizeInfo>
      <Key>StampId_GPPS0064</Key>
      <Value>Necessidades especiais</Value>
      <Comment />
      <Link />
      <FontSize>12</FontSize>
      <FontName>Segoe UI</FontName>
      <MaxNumber>12</MaxNumber>
    </LocalizeInfo>
    <LocalizeInfo>
      <Key>StampId_GPPS0067</Key>
      <Value>Localização atual do paciente</Value>
      <Comment />
      <Link />
      <FontSize>12</FontSize>
      <FontName>Segoe UI</FontName>
      <MaxNumber>12</MaxNumber>
    </LocalizeInfo>
    <LocalizeInfo>
      <Key>StampId_GPPS0029</Key>
      <Value>Residência do paciente(Enfermaria)</Value>
      <Comment />
      <Link />
      <FontSize>12</FontSize>
      <FontName>Segoe UI</FontName>
      <MaxNumber>12</MaxNumber>
    </LocalizeInfo>
    <LocalizeInfo>
      <Key>StampId_GPPS0065</Key>
      <Value>Estado do paciente</Value>
      <Comment />
      <Link />
      <FontSize>12</FontSize>
      <FontName>Segoe UI</FontName>
      <MaxNumber>12</MaxNumber>
    </LocalizeInfo>
    <LocalizeInfo>
      <Key>StampId_00400300</Key>
      <Value>Duração total de exposição</Value>
      <Comment />
      <Link />
      <FontSize>12</FontSize>
      <FontName>Segoe UI</FontName>
      <MaxNumber>12</MaxNumber>
    </LocalizeInfo>
    <LocalizeInfo>
      <Key>StampId_00400302</Key>
      <Value>Dose de entrada</Value>
      <Comment />
      <Link />
      <FontSize>12</FontSize>
      <FontName>Segoe UI</FontName>
      <MaxNumber>12</MaxNumber>
    </LocalizeInfo>
    <LocalizeInfo>
      <Key>StampId_00400303:0</Key>
      <Value>Área exposta</Value>
      <Comment />
      <Link />
      <FontSize>12</FontSize>
      <FontName>Segoe UI</FontName>
      <MaxNumber>12</MaxNumber>
    </LocalizeInfo>
    <LocalizeInfo>
      <Key>StampId_00400306</Key>
      <Value>Detetor de entrada[mm]</Value>
      <Comment />
      <Link />
      <FontSize>12</FontSize>
      <FontName>Segoe UI</FontName>
      <MaxNumber>12</MaxNumber>
    </LocalizeInfo>
    <LocalizeInfo>
      <Key>StampId_GSPR0006</Key>
      <Value>Número de colocação de pedido</Value>
      <Comment />
      <Link />
      <FontSize>12</FontSize>
      <FontName>Segoe UI</FontName>
      <MaxNumber>12</MaxNumber>
    </LocalizeInfo>
    <LocalizeInfo>
      <Key>StampId_GSPR0005</Key>
      <Value>Filtrar número de pedido</Value>
      <Comment />
      <Link />
      <FontSize>12</FontSize>
      <FontName>Segoe UI</FontName>
      <MaxNumber>12</MaxNumber>
    </LocalizeInfo>
    <LocalizeInfo>
      <Key>StampId_GPPS0066</Key>
      <Value>Confidencialidade do paciente</Value>
      <Comment />
      <Link />
      <FontSize>12</FontSize>
      <FontName>Segoe UI</FontName>
      <MaxNumber>12</MaxNumber>
    </LocalizeInfo>
    <LocalizeInfo>
      <Key>StampId_00408302</Key>
      <Value>Inc. plano de dose(mGy)</Value>
      <Comment />
      <Link />
      <FontSize>12</FontSize>
      <FontName>Segoe UI</FontName>
      <MaxNumber>12</MaxNumber>
    </LocalizeInfo>
    <LocalizeInfo>
      <Key>StampId_00311001</Key>
      <Value>Definir número de etiqueta de exame</Value>
      <Comment />
      <Link />
      <FontSize>12</FontSize>
      <FontName>Segoe UI</FontName>
      <MaxNumber>12</MaxNumber>
    </LocalizeInfo>
    <LocalizeInfo>
      <Key>StampId_00311002</Key>
      <Value>Definir nome de página</Value>
      <Comment />
      <Link />
      <FontSize>12</FontSize>
      <FontName>Segoe UI</FontName>
      <MaxNumber>12</MaxNumber>
    </LocalizeInfo>
    <LocalizeInfo>
      <Key>StampId_00311003</Key>
      <Value>Definir nome de grupo</Value>
      <Comment />
      <Link />
      <FontSize>12</FontSize>
      <FontName>Segoe UI</FontName>
      <MaxNumber>12</MaxNumber>
    </LocalizeInfo>
    <LocalizeInfo>
      <Key>StampId_00311004</Key>
      <Value>Definir nome de etiqueta</Value>
      <Comment />
      <Link />
      <FontSize>12</FontSize>
      <FontName>Segoe UI</FontName>
      <MaxNumber>12</MaxNumber>
    </LocalizeInfo>
    <LocalizeInfo>
      <Key>StampId_00311005:0</Key>
      <Value>Número de etiqueta de exame do utilizador</Value>
      <Comment />
      <Link />
      <FontSize>12</FontSize>
      <FontName>Segoe UI</FontName>
      <MaxNumber>12</MaxNumber>
    </LocalizeInfo>
    <LocalizeInfo>
      <Key>StampId_00311007</Key>
      <Value>Nome de grupo do utilizador</Value>
      <Comment />
      <Link />
      <FontSize>12</FontSize>
      <FontName>Segoe UI</FontName>
      <MaxNumber>12</MaxNumber>
    </LocalizeInfo>
    <LocalizeInfo>
      <Key>StampId_00311008</Key>
      <Value>Nome de etiqueta de utilizador</Value>
      <Comment />
      <Link />
      <FontSize>12</FontSize>
      <FontName>Segoe UI</FontName>
      <MaxNumber>12</MaxNumber>
    </LocalizeInfo>
    <LocalizeInfo>
      <Key>StampId_00311100;00311060</Key>
      <Value>CódigoControloRaioX</Value>
      <Comment />
      <Link />
      <FontSize>12</FontSize>
      <FontName>Segoe UI</FontName>
      <MaxNumber>12</MaxNumber>
    </LocalizeInfo>
    <LocalizeInfo>
      <Key>StampId_00311100;00311061</Key>
      <Value>Número de tubo</Value>
      <Comment />
      <Link />
      <FontSize>12</FontSize>
      <FontName>Segoe UI</FontName>
      <MaxNumber>12</MaxNumber>
    </LocalizeInfo>
    <LocalizeInfo>
      <Key>StampId_00311018</Key>
      <Value>Dispositivo de saída</Value>
      <Comment />
      <Link />
      <FontSize>12</FontSize>
      <FontName>Segoe UI</FontName>
      <MaxNumber>12</MaxNumber>
    </LocalizeInfo>
    <LocalizeInfo>
      <Key>StampId_00311105;00311081:3</Key>
      <Value>DL(Processo G)</Value>
      <Comment />
      <Link />
      <FontSize>12</FontSize>
      <FontName>Segoe UI</FontName>
      <MaxNumber>12</MaxNumber>
    </LocalizeInfo>
    <LocalizeInfo>
      <Key>StampId_00311105;00311081:4</Key>
      <Value>DH(Processo G)</Value>
      <Comment />
      <Link />
      <FontSize>12</FontSize>
      <FontName>Segoe UI</FontName>
      <MaxNumber>12</MaxNumber>
    </LocalizeInfo>
    <LocalizeInfo>
      <Key>StampId_00311105;00311082:1</Key>
      <Value>Mask Size(E-Process)</Value>
      <Comment />
      <Link />
      <FontSize>12</FontSize>
      <FontName>Segoe UI</FontName>
      <MaxNumber>64</MaxNumber>
    </LocalizeInfo>
    <LocalizeInfo>
      <Key>StampId_00311105;00311084:1</Key>
      <Value>Mask Size(F-Process)</Value>
      <Comment />
      <Link />
      <FontSize>12</FontSize>
      <FontName>Segoe UI</FontName>
      <MaxNumber>64</MaxNumber>
    </LocalizeInfo>
    <LocalizeInfo>
      <Key>StampId_003110CC:1</Key>
      <Value>Valor S </Value>
      <Comment />
      <Link />
      <FontSize>12</FontSize>
      <FontName>Segoe UI</FontName>
      <MaxNumber>12</MaxNumber>
    </LocalizeInfo>
    <LocalizeInfo>
      <Key>StampId_003110CC:0</Key>
      <Value>Valor G</Value>
      <Comment />
      <Link />
      <FontSize>12</FontSize>
      <FontName>Segoe UI</FontName>
      <MaxNumber>12</MaxNumber>
    </LocalizeInfo>
    <LocalizeInfo>
      <Key>StampId_003110CA:0</Key>
      <Value>Deslocar</Value>
      <Comment />
      <Link />
      <FontSize>12</FontSize>
      <FontName>Segoe UI</FontName>
      <MaxNumber>12</MaxNumber>
    </LocalizeInfo>
    <LocalizeInfo>
      <Key>StampId_003110CA:1</Key>
      <Value>Rodar</Value>
      <Comment />
      <Link />
      <FontSize>12</FontSize>
      <FontName>Segoe UI</FontName>
      <MaxNumber>12</MaxNumber>
    </LocalizeInfo>
    <LocalizeInfo>
      <Key>StampId_0031107B:0</Key>
      <Value>E ON/OFF</Value>
      <Comment />
      <Link />
      <FontSize>12</FontSize>
      <FontName>Segoe UI</FontName>
      <MaxNumber>12</MaxNumber>
    </LocalizeInfo>
    <LocalizeInfo>
      <Key>StampId_0031107C:0</Key>
      <Value>F ON/OFF</Value>
      <Comment />
      <Link />
      <FontSize>12</FontSize>
      <FontName>Segoe UI</FontName>
      <MaxNumber>12</MaxNumber>
    </LocalizeInfo>
    <LocalizeInfo>
      <Key>StampId_00311105;00311086:0</Key>
      <Value>H ID (HE ou HF)</Value>
      <Comment />
      <Link />
      <FontSize>12</FontSize>
      <FontName>Segoe UI</FontName>
      <MaxNumber>12</MaxNumber>
    </LocalizeInfo>
    <LocalizeInfo>
      <Key>StampId_00311105;00311086:2</Key>
      <Value>HF-STANDARD</Value>
      <Comment />
      <Link />
      <FontSize>12</FontSize>
      <FontName>Segoe UI</FontName>
      <MaxNumber>12</MaxNumber>
    </LocalizeInfo>
    <LocalizeInfo>
      <Key>StampId_00311105;00311086:1</Key>
      <Value>HE-STANDARD</Value>
      <Comment />
      <Link />
      <FontSize>12</FontSize>
      <FontName>Segoe UI</FontName>
      <MaxNumber>12</MaxNumber>
    </LocalizeInfo>
    <LocalizeInfo>
      <Key>StampId_00311105;00311087:1</Key>
      <Value>HF-b2</Value>
      <Comment />
      <Link />
      <FontSize>12</FontSize>
      <FontName>Segoe UI</FontName>
      <MaxNumber>12</MaxNumber>
    </LocalizeInfo>
    <LocalizeInfo>
      <Key>StampId_00311105;00311087:0</Key>
      <Value>HF-b1</Value>
      <Comment />
      <Link />
      <FontSize>12</FontSize>
      <FontName>Segoe UI</FontName>
      <MaxNumber>12</MaxNumber>
    </LocalizeInfo>
    <LocalizeInfo>
      <Key>StampId_00311105;00311087:3</Key>
      <Value>HE-bh</Value>
      <Comment />
      <Link />
      <FontSize>12</FontSize>
      <FontName>Segoe UI</FontName>
      <MaxNumber>12</MaxNumber>
    </LocalizeInfo>
    <LocalizeInfo>
      <Key>StampId_00311105;00311087:2</Key>
      <Value>HE-bl</Value>
      <Comment />
      <Link />
      <FontSize>12</FontSize>
      <FontName>Segoe UI</FontName>
      <MaxNumber>12</MaxNumber>
    </LocalizeInfo>
    <LocalizeInfo>
      <Key>DisplayFormatId_undefined</Key>
      <Value>Indefinida</Value>
      <Comment />
      <Link />
      <FontSize>12</FontSize>
      <FontName>Segoe UI</FontName>
      <MaxNumber>12</MaxNumber>
    </LocalizeInfo>
    <LocalizeInfo>
      <Key>DisplayFormatId_GN000</Key>
      <Value>Indefinida</Value>
      <Comment />
      <Link />
      <FontSize>12</FontSize>
      <FontName>Segoe UI</FontName>
      <MaxNumber>12</MaxNumber>
    </LocalizeInfo>
    <LocalizeInfo>
      <Key>DisplayFormatId_GN001</Key>
      <Value>Converter para Hex</Value>
      <Comment />
      <Link />
      <FontSize>12</FontSize>
      <FontName>Segoe UI</FontName>
      <MaxNumber>12</MaxNumber>
    </LocalizeInfo>
    <LocalizeInfo>
      <Key>DisplayFormatId_GN002</Key>
      <Value />
      <Comment />
      <Link />
      <FontSize>12</FontSize>
      <FontName>Segoe UI</FontName>
      <MaxNumber>12</MaxNumber>
    </LocalizeInfo>
    <LocalizeInfo>
      <Key>DisplayFormatId_GN003</Key>
      <Value>Dividido por 100</Value>
      <Comment />
      <Link />
      <FontSize>12</FontSize>
      <FontName>Segoe UI</FontName>
      <MaxNumber>12</MaxNumber>
    </LocalizeInfo>
    <LocalizeInfo>
      <Key>DisplayFormatId_GN005</Key>
      <Value>Decimal abaixo 2</Value>
      <Comment />
      <Link />
      <FontSize>12</FontSize>
      <FontName>Segoe UI</FontName>
      <MaxNumber>12</MaxNumber>
    </LocalizeInfo>
    <LocalizeInfo>
      <Key>DisplayFormatId_GN007</Key>
      <Value>Letras maiuscula</Value>
      <Comment />
      <Link />
      <FontSize>12</FontSize>
      <FontName>Segoe UI</FontName>
      <MaxNumber>12</MaxNumber>
    </LocalizeInfo>
    <LocalizeInfo>
      <Key>DisplayFormatId_DA000</Key>
      <Value />
      <Comment />
      <Link />
      <FontSize>12</FontSize>
      <FontName>Segoe UI</FontName>
      <MaxNumber>12</MaxNumber>
    </LocalizeInfo>
    <LocalizeInfo>
      <Key>DisplayFormatId_DA001</Key>
      <Value>M- D-AAAA</Value>
      <Comment />
      <Link />
      <FontSize>12</FontSize>
      <FontName>Segoe UI</FontName>
      <MaxNumber>12</MaxNumber>
    </LocalizeInfo>
    <LocalizeInfo>
      <Key>DisplayFormatId_DA002</Key>
      <Value>MM-DD-AAAA</Value>
      <Comment />
      <Link />
      <FontSize>12</FontSize>
      <FontName>Segoe UI</FontName>
      <MaxNumber>12</MaxNumber>
    </LocalizeInfo>
    <LocalizeInfo>
      <Key>DisplayFormatId_DA003</Key>
      <Value>D- M-AAAA</Value>
      <Comment />
      <Link />
      <FontSize>12</FontSize>
      <FontName>Segoe UI</FontName>
      <MaxNumber>12</MaxNumber>
    </LocalizeInfo>
    <LocalizeInfo>
      <Key>DisplayFormatId_DA004</Key>
      <Value>DD-MM-AAAA</Value>
      <Comment />
      <Link />
      <FontSize>12</FontSize>
      <FontName>Segoe UI</FontName>
      <MaxNumber>12</MaxNumber>
    </LocalizeInfo>
    <LocalizeInfo>
      <Key>DisplayFormatId_DA010</Key>
      <Value />
      <Comment />
      <Link />
      <FontSize>12</FontSize>
      <FontName>Segoe UI</FontName>
      <MaxNumber>12</MaxNumber>
    </LocalizeInfo>
    <LocalizeInfo>
      <Key>DisplayFormatId_DA011</Key>
      <Value />
      <Comment />
      <Link />
      <FontSize>12</FontSize>
      <FontName>Segoe UI</FontName>
      <MaxNumber>12</MaxNumber>
    </LocalizeInfo>
    <LocalizeInfo>
      <Key>DisplayFormatId_TM000</Key>
      <Value />
      <Comment />
      <Link />
      <FontSize>12</FontSize>
      <FontName>Segoe UI</FontName>
      <MaxNumber>12</MaxNumber>
    </LocalizeInfo>
    <LocalizeInfo>
      <Key>DisplayFormatId_TM001</Key>
      <Value />
      <Comment />
      <Link />
      <FontSize>12</FontSize>
      <FontName>Segoe UI</FontName>
      <MaxNumber>12</MaxNumber>
    </LocalizeInfo>
    <LocalizeInfo>
      <Key>DisplayFormatId_TM002</Key>
      <Value>hh:mm:ss</Value>
      <Comment />
      <Link />
      <FontSize>12</FontSize>
      <FontName>Segoe UI</FontName>
      <MaxNumber>12</MaxNumber>
    </LocalizeInfo>
    <LocalizeInfo>
      <Key>DisplayFormatId_TM003</Key>
      <Value>hh:mm</Value>
      <Comment />
      <Link />
      <FontSize>12</FontSize>
      <FontName>Segoe UI</FontName>
      <MaxNumber>12</MaxNumber>
    </LocalizeInfo>
    <LocalizeInfo>
      <Key>DisplayFormatId_AS000</Key>
      <Value>(Anos), (Meses), (Dias)</Value>
      <Comment />
      <Link />
      <FontSize>12</FontSize>
      <FontName>Segoe UI</FontName>
      <MaxNumber>12</MaxNumber>
    </LocalizeInfo>
    <LocalizeInfo>
      <Key>DisplayFormatId_AS001</Key>
      <Value />
      <Comment />
      <Link />
      <FontSize>12</FontSize>
      <FontName>Segoe UI</FontName>
      <MaxNumber>12</MaxNumber>
    </LocalizeInfo>
    <LocalizeInfo>
      <Key>DisplayFormatId_SX000</Key>
      <Value />
      <Comment />
      <Link />
      <FontSize>12</FontSize>
      <FontName>Segoe UI</FontName>
      <MaxNumber>12</MaxNumber>
    </LocalizeInfo>
    <LocalizeInfo>
      <Key>DisplayFormatId_SX001</Key>
      <Value />
      <Comment />
      <Link />
      <FontSize>12</FontSize>
      <FontName>Segoe UI</FontName>
      <MaxNumber>12</MaxNumber>
    </LocalizeInfo>
    <LocalizeInfo>
      <Key>DisplayFormatId_SX002</Key>
      <Value>(Homem), (Senhora), (Indefinido)</Value>
      <Comment />
      <Link />
      <FontSize>12</FontSize>
      <FontName>Segoe UI</FontName>
      <MaxNumber>12</MaxNumber>
    </LocalizeInfo>
    <LocalizeInfo>
      <Key>DisplayFormatId_SX003</Key>
      <Value>Homem, Senhora, Indefinido</Value>
      <Comment />
      <Link />
      <FontSize>12</FontSize>
      <FontName>Segoe UI</FontName>
      <MaxNumber>12</MaxNumber>
    </LocalizeInfo> 
    <LocalizeInfo>
      <Key>DisplayFormatId_PN000</Key>
      <Value />
      <Comment />
      <Link />
      <FontSize>12</FontSize>
      <FontName>Segoe UI</FontName>
      <MaxNumber>64</MaxNumber>
    </LocalizeInfo>
    <LocalizeInfo>
      <Key>DisplayFormatId_PN001</Key>
      <Value>^(cap)into single byte space</Value>
      <Comment />
      <Link />
      <FontSize>12</FontSize>
      <FontName>Segoe UI</FontName>
      <MaxNumber>64</MaxNumber>
    </LocalizeInfo>
  </LocalizeList>
</LocalizeDictionary>